maudio/MorseTable.py
maudio/__init__.py
maudio/__main__.py
maudio/conf.py
maudio-0.0.2.dist-info/licenses/LICENSE
maudio-0.0.2.dist-info/METADATA
maudio-0.0.2.dist-info/WHEEL
maudio-0.0.2.dist-info/entry_points.txt
maudio-0.0.2.dist-info/top_level.txt
maudio-0.0.2.dist-info/RECORD
