Metadata-Version: 2.4
Name: maudio
Version: 0.0.2
Summary: Minimal Morse code audio encoder ( WAV format )
Home-page: https://github.com/Mohd-Sinan/maudio
Author: Mohammed Sinan KH
Author-email: devsinankh123@gmail.com
Maintainer: Mohammed Sinan KH
License: MIT
Project-URL: Source, https://github.com/Mohd-Sinan/maudio
Project-URL: Tracker, https://github.com/Mohd-Sinan/maudio/issues
Keywords: morse code audio generation
Classifier: Development Status :: 3 - Alpha
Classifier: License :: OSI Approved :: MIT License
Classifier: Intended Audience :: Developers
Classifier: Topic :: Multimedia :: Sound/Audio
Classifier: Programming Language :: Python :: 3.2
Classifier: Programming Language :: Python :: 3.6
Classifier: Programming Language :: Python :: 3.7
Classifier: Programming Language :: Python :: 3.8
Classifier: Programming Language :: Python :: 3.9
Requires-Python: >=3.6
License-File: LICENSE
Dynamic: author
Dynamic: author-email
Dynamic: classifier
Dynamic: description
Dynamic: description-content-type
Dynamic: home-page
Dynamic: keywords
Dynamic: license
Dynamic: license-file
Dynamic: maintainer
Dynamic: project-url
Dynamic: requires-python
Dynamic: summary
